evext/__init__.py
evext/calc.py
evext-1.0.0.dist-info/METADATA
evext-1.0.0.dist-info/WHEEL
evext-1.0.0.dist-info/top_level.txt
evext-1.0.0.dist-info/RECORD
